quantification/__init__.py
quantification/api/__init__.py
quantification/api/akshare/__init__.py
quantification/api/akshare/akshare.py
quantification/api/akshare/delegate/__init__.py
quantification/api/akshare/delegate/macro_china_fdi.py
quantification/api/akshare/delegate/macro_china_lpr.py
quantification/api/akshare/delegate/macro_china_qyspjg.py
quantification/api/akshare/delegate/macro_china_shrzgm.py
quantification/api/akshare/delegate/macro_cnbs.py
quantification/api/akshare/delegate/stock_zh_a_hist.py
quantification/api/akshare/setting.py
quantification/api/api.py
quantification/api/api.pyi
quantification/api/spider/__init__.py
quantification/api/spider/delegate/__init__.py
quantification/api/spider/delegate/baidu_index.py
quantification/api/spider/setting.py
quantification/api/spider/spider.py
quantification/api/tushare/__init__.py
quantification/api/tushare/delegate/__init__.py
quantification/api/tushare/delegate/balancesheet.py
quantification/api/tushare/delegate/cashflow.py
quantification/api/tushare/delegate/common.py
quantification/api/tushare/delegate/daily_basic.py
quantification/api/tushare/delegate/fina_indicator.py
quantification/api/tushare/delegate/income.py
quantification/api/tushare/delegate/index_daily.py
quantification/api/tushare/delegate/pro_bar.py
quantification/api/tushare/setting.py
quantification/api/tushare/tushare.py
quantification/core/__init__.py
quantification/core/asset/__init__.py
quantification/core/asset/base_asset.py
quantification/core/asset/base_broker.py
quantification/core/asset/broker.py
quantification/core/asset/cash.py
quantification/core/asset/stock.py
quantification/core/cache.py
quantification/core/configure.py
quantification/core/data/__init__.py
quantification/core/data/base_api.py
quantification/core/data/base_delegate.py
quantification/core/data/field.py
quantification/core/data/panel.py
quantification/core/env.py
quantification/core/logger.py
quantification/core/strategy/__init__.py
quantification-0.1.3.dist-info/METADATA
quantification-0.1.3.dist-info/WHEEL
quantification-0.1.3.dist-info/RECORD
