Metadata-Version: 2.3
Name: quantification
Version: 0.1.3
Summary: 
License: MIT
Author: realhuhu
Author-email: 2661467107@qq.com
Requires-Python: >=3.13,<4.0
Classifier: License :: OSI Approved :: MIT License
Classifier: Programming Language :: Python :: 3
Classifier: Programming Language :: Python :: 3.13
Requires-Dist: akshare (>=1.17.22,<2.0.0)
Requires-Dist: loguru (>=0.7.3,<0.8.0)
Requires-Dist: pycryptodome (>=3.23.0,<4.0.0)
Requires-Dist: pydantic (>=2.11.7,<3.0.0)
Requires-Dist: pydantic-settings (>=2.10.1,<3.0.0)
Requires-Dist: tushare (>=1.4.21,<2.0.0)
